README.md
setup.py
salure_preprocessors/__init__.py
salure_preprocessors.egg-info/PKG-INFO
salure_preprocessors.egg-info/SOURCES.txt
salure_preprocessors.egg-info/dependency_links.txt
salure_preprocessors.egg-info/not-zip-safe
salure_preprocessors.egg-info/requires.txt
salure_preprocessors.egg-info/top_level.txt
salure_preprocessors/preprocessors/__init__.py
salure_preprocessors/preprocessors/pandas_preprocessors.py